{
  "type": "ComicReaderPage",
  "i18n": {
    "nextPageLabel": {
      "en": "Next",
      "de": "Weiter",
      "zh": "下一页"
    },
    "prevPageLabel": {
      "en": "Back",
      "de": "Zurück",
      "zh": "上一页"
    },
    "currentPageLabel": {
      "en": "Page",
      "de": "Seite",
      "zh": "当前页"
    },
    "backLinkLabel": {
      "en": "Back to Comics",
      "de": "Zurück nach Comics",
      "zh": "回到漫画列表"
    }
  },
  "backLinkUrl": {
    "pageName": "comics",
    "queries": {}
  }
}